nonebot_plugin_color_see_see-0.2.0.dist-info/METADATA
nonebot_plugin_color_see_see-0.2.0.dist-info/WHEEL
nonebot_plugin_color_see_see-0.2.0.dist-info/entry_points.txt
nonebot_plugin_color_see_see-0.2.0.dist-info/licenses/LICENSE
nonebot_plugin_color_see_see/__init__.py
nonebot_plugin_color_see_see/data_source.py
nonebot_plugin_color_see_see/resources/arial.ttf
nonebot_plugin_color_see_see-0.2.0.dist-info/RECORD
