Metadata-Version: 2.1
Name: nonebot-plugin-color-see-see
Version: 0.2.0
Summary: 给你点颜色瞧瞧？给我点颜色瞧瞧（让我康康！
Author-Email: FrostN0v0 <1614591760@qq.com>
License: MIT
Requires-Python: >=3.10
Requires-Dist: nonebot2>=2.3.3
Requires-Dist: pillow>=10.4.0
Requires-Dist: nonebot-plugin-alconna>=0.52.3
Requires-Dist: nonebot-plugin-uninfo>=0.4.1
Provides-Extra: adapters
Requires-Dist: nonebot-adapter-onebot>=2.4.5; extra == "adapters"
